README.md
setup.cfg
setup.py
raziel/Raziel.py
raziel/__init__.py
raziel/debug.py
raziel/vocab.py
raziel.egg-info/PKG-INFO
raziel.egg-info/SOURCES.txt
raziel.egg-info/dependency_links.txt
raziel.egg-info/requires.txt
raziel.egg-info/top_level.txt
raziel/generators/__init__.py
raziel/layers/DropConnectLSTM.py
raziel/layers/WeightedMean.py
raziel/layers/__init__.py
raziel/layers/simpleCRF.py
raziel/plugins/__init__.py
raziel/plugins/plugin_bert.py
raziel/plugins/plugin_chars.py
raziel/plugins/plugin_custom.py
raziel/plugins/plugin_elmo.py
raziel/plugins/plugin_fasttext.py
raziel/plugins/plugin_flair.py
raziel/plugins/plugin_label.py
raziel/plugins/plugin_list.py
raziel/plugins/plugin_multilabel.py