Metadata-Version: 2.1
Name: raziel
Version: 0.0.4.post1
Summary: A Data Transformation helper
Home-page: https://git.informatik.uni-leipzig.de/mai13ivw/raziel
Author: Janos Borst
Author-email: borst@informatik.uni-leipzig.de
License: UNKNOWN
Platform: UNKNOWN
Classifier: Programming Language :: Python :: 3
Classifier: License :: OSI Approved :: MIT License
Classifier: Operating System :: OS Independent
